chemotaxissimulation.py
photokineticanalysis.py
Photosimulator-0.0.1.dist-info/LICENSE
Photosimulator-0.0.1.dist-info/METADATA
Photosimulator-0.0.1.dist-info/WHEEL
Photosimulator-0.0.1.dist-info/top_level.txt
Photosimulator-0.0.1.dist-info/RECORD
