Metadata-Version: 2.1
Name: Photosimulator
Version: 0.0.1
Summary: A photokinetic analysis package developed for the DeForest Group
Author-email: Brizzia Munoz Robles <bmunozro@uw.edu>
Project-URL: Homepage, https://github.com/bmunozro1/Photosimulator
Project-URL: Issues, https://github.com/bmunozro1/Photosimulator
Classifier: Programming Language :: Python :: 3
Classifier: License :: OSI Approved :: MIT License
Classifier: Operating System :: OS Independent
Requires-Python: >=3.8
License-File: LICENSE
